README.md
setup.cfg
setup.py
tuyapy/__init__.py
tuyapy/tuyaapi.py
tuyapy.egg-info/PKG-INFO
tuyapy.egg-info/SOURCES.txt
tuyapy.egg-info/dependency_links.txt
tuyapy.egg-info/top_level.txt
tuyapy/devices/__init__.py
tuyapy/devices/base.py
tuyapy/devices/climate.py
tuyapy/devices/cover.py
tuyapy/devices/factory.py
tuyapy/devices/fan.py
tuyapy/devices/light.py
tuyapy/devices/lock.py
tuyapy/devices/remote.py
tuyapy/devices/scene.py
tuyapy/devices/switch.py