Metadata-Version: 2.1
Name: tuyapy
Version: 0.1.4
Summary: A Python library for Tuya Device with Python 3+
Home-page: UNKNOWN
Author: Tuya Inc.
Author-email: tuyasmart@tuya.com
License: UNKNOWN
Platform: UNKNOWN
Classifier: Programming Language :: Python :: 3
Classifier: License :: OSI Approved :: MIT License
Classifier: Operating System :: OS Independent
